_proto/jfml/hosting_gateway/v1/build_upload_url_pb2.py
_proto/jfml/hosting_gateway/v1/build_upload_url_pb2.pyi
_proto/jfml/hosting_gateway/v1/build_upload_url_pb2_grpc.py
_proto/jfml/hosting_gateway/v1/hosting_gateway_service_pb2.py
_proto/jfml/hosting_gateway/v1/hosting_gateway_service_pb2.pyi
_proto/jfml/hosting_gateway/v1/hosting_gateway_service_pb2_grpc.py
_proto/jfml/model_version/v1/artifact_pb2.py
_proto/jfml/model_version/v1/artifact_pb2.pyi
_proto/jfml/model_version/v1/artifact_pb2_grpc.py
_proto/jfml/model_version/v1/build_spec_pb2.py
_proto/jfml/model_version/v1/build_spec_pb2.pyi
_proto/jfml/model_version/v1/build_spec_pb2_grpc.py
_proto/jfml/model_version/v1/model_repository_spec_pb2.py
_proto/jfml/model_version/v1/model_repository_spec_pb2.pyi
_proto/jfml/model_version/v1/model_repository_spec_pb2_grpc.py
_proto/jfml/model_version/v1/model_version_framework_pb2.py
_proto/jfml/model_version/v1/model_version_framework_pb2.pyi
_proto/jfml/model_version/v1/model_version_framework_pb2_grpc.py
_proto/jfml/model_version/v1/model_version_manager_service_pb2.py
_proto/jfml/model_version/v1/model_version_manager_service_pb2.pyi
_proto/jfml/model_version/v1/model_version_manager_service_pb2_grpc.py
_proto/jfml/model_version/v1/model_version_pb2.py
_proto/jfml/model_version/v1/model_version_pb2.pyi
_proto/jfml/model_version/v1/model_version_pb2_grpc.py
_proto/qwak/administration/account/v1/account_pb2.py
_proto/qwak/administration/account/v1/account_pb2.pyi
_proto/qwak/administration/account/v1/account_pb2_grpc.py
_proto/qwak/administration/account/v1/account_service_pb2.py
_proto/qwak/administration/account/v1/account_service_pb2.pyi
_proto/qwak/administration/account/v1/account_service_pb2_grpc.py
_proto/qwak/administration/account/v1/jfrog_tenant_details_pb2.py
_proto/qwak/administration/account/v1/jfrog_tenant_details_pb2.pyi
_proto/qwak/administration/account/v1/jfrog_tenant_details_pb2_grpc.py
_proto/qwak/administration/account/v1/personalization_pb2.py
frogml_core-0.0.121.dist-info/METADATA
frogml_core-0.0.121.dist-info/WHEEL
frogml_core-0.0.121.dist-info/RECORD
