Metadata-Version: 2.3
Name: frogml-core
Version: 0.0.121
Summary: frogml contains the necessary objects and communication tools for using the JFrog ml Platform
License: Apache-2.0
Keywords: mlops,ml,deployment,serving,model
Author: JFrog
Requires-Python: >=3.9,<3.12
Classifier: License :: OSI Approved :: Apache Software License
Classifier: Operating System :: OS Independent
Classifier: Programming Language :: Python :: 3
Classifier: Programming Language :: Python :: 3.9
Classifier: Programming Language :: Python :: 3.10
Classifier: Programming Language :: Python :: 3.11
Classifier: Programming Language :: Python :: Implementation :: CPython
Classifier: Topic :: Scientific/Engineering :: Artificial Intelligence
Provides-Extra: feature-store
Requires-Dist: PyYAML (>=6.0.2)
Requires-Dist: cachetools
Requires-Dist: chevron (==0.14.0)
Requires-Dist: cloudpickle (==2.2.1) ; extra == "feature-store"
Requires-Dist: dacite (==1.8.1)
Requires-Dist: dependency-injector (>=4.0)
Requires-Dist: filelock
Requires-Dist: grpcio (>=1.57.0)
Requires-Dist: joblib (>=1.3.2,<2.0.0)
Requires-Dist: marshmallow-dataclass (>=8.5.8,<9.0.0)
Requires-Dist: protobuf (>=4.25.8)
Requires-Dist: pyarrow (>=20.0.0) ; extra == "feature-store"
Requires-Dist: pyathena (>=2.2.0,!=2.18.0) ; extra == "feature-store"
Requires-Dist: pydantic
Requires-Dist: pyspark (==3.4.2) ; extra == "feature-store"
Requires-Dist: python-jose[cryptography] (>=3.4.0)
Requires-Dist: python-json-logger (>=2.0.2)
Requires-Dist: requests
Requires-Dist: retrying (==1.3.4)
Requires-Dist: tqdm
Requires-Dist: typeguard (>=2,<3)
Project-URL: Home page, https://www.jfrog.com/
